grafiki/__init__.py
grafiki/core.py
grafiki/types.py
grafiki_bridge-0.2.0.dist-info/licenses/LICENSE
grafiki_bridge-0.2.0.dist-info/METADATA
grafiki_bridge-0.2.0.dist-info/WHEEL
grafiki_bridge-0.2.0.dist-info/top_level.txt
grafiki_bridge-0.2.0.dist-info/RECORD
