Metadata-Version: 2.4
Name: grafiki-bridge
Version: 0.2.0
Summary: Send data from Jupyter notebooks to the grafiki web dashboard.
Author-email: leberkaassemmel <leber.kaas.semel@gmail.com>
License: MIT
Project-URL: Homepage, https://github.com/leberkaassemmel/grafiki-bridge
Requires-Python: >=3.7
License-File: LICENSE
Requires-Dist: pandas>=1.0.0
Requires-Dist: ipython>=7.0.0
Dynamic: license-file
